pydantic_store/__init__.py
pydantic_store/dbm.py
pydantic_store/dbm_sqlite.py
pydantic_store/models.py
pydantic_store/py.typed
pydantic_store-0.1.0.dist-info/METADATA
pydantic_store-0.1.0.dist-info/WHEEL
pydantic_store-0.1.0.dist-info/licenses/LICENSE.md
pydantic_store-0.1.0.dist-info/RECORD
