Metadata-Version: 2.4
Name: pydantic-store
Version: 0.1.0
Summary: Helper models and backports
License: MIT
License-File: LICENSE.md
Author: mySociety
Author-email: alex.parsons@mysociety.org
Requires-Python: >=3.9,<4.0
Classifier: License :: OSI Approved :: MIT License
Classifier: Programming Language :: Python :: 3
Classifier: Programming Language :: Python :: 3.9
Classifier: Programming Language :: Python :: 3.10
Classifier: Programming Language :: Python :: 3.11
Classifier: Programming Language :: Python :: 3.12
Classifier: Programming Language :: Python :: 3.13
Classifier: Programming Language :: Python :: 3.14
Requires-Dist: pydantic (>=2.0)
Project-URL: Homepage, https://github.com/mysociety/pydantic-store
Project-URL: Repository, https://github.com/mysociety/pydantic-store
